guillotina_statsd/__init__.py
guillotina_statsd/install.py
guillotina_statsd/middleware.py
guillotina_statsd/utility.py
guillotina_statsd-1.0.6.dist-info/DESCRIPTION.rst
guillotina_statsd-1.0.6.dist-info/METADATA
guillotina_statsd-1.0.6.dist-info/RECORD
guillotina_statsd-1.0.6.dist-info/WHEEL
guillotina_statsd-1.0.6.dist-info/metadata.json
guillotina_statsd-1.0.6.dist-info/top_level.txt
