Metadata-Version: 2.0
Name: guillotina-statsd
Version: 1.0.6
Summary: Integrate statsd into guillotina
Home-page: https://github.com/guillotinaweb/guillotina_statsd
Author: Nathan Van Gheem
Author-email: vangheem@gmail.com
License: UNKNOWN
Platform: UNKNOWN
Requires-Dist: guillotina (>=2.1.5)
Requires-Dist: aiostatsd
Provides-Extra: test
Requires-Dist: pytest; extra == 'test'
